haizelabs_api/__init__.py
haizelabs_api/_base_client.py
haizelabs_api/_client.py
haizelabs_api/_compat.py
haizelabs_api/_constants.py
haizelabs_api/_exceptions.py
haizelabs_api/_files.py
haizelabs_api/_models.py
haizelabs_api/_qs.py
haizelabs_api/_resource.py
haizelabs_api/_response.py
haizelabs_api/_streaming.py
haizelabs_api/_types.py
haizelabs_api/_version.py
haizelabs_api/py.typed
haizelabs_api/_utils/__init__.py
haizelabs_api/_utils/_logs.py
haizelabs_api/_utils/_proxy.py
haizelabs_api/_utils/_reflection.py
haizelabs_api/_utils/_streams.py
haizelabs_api/_utils/_sync.py
haizelabs_api/_utils/_transform.py
haizelabs_api/_utils/_typing.py
haizelabs_api/_utils/_utils.py
haizelabs_api/lib/.keep
haizelabs_api/resources/__init__.py
haizelabs_api/resources/judges.py
haizelabs_api/resources/monitoring.py
haizelabs_api/resources/testing.py
haizelabs_api/types/__init__.py
haizelabs_api/types/judge_call_params.py
haizelabs_api/types/judge_call_response.py
haizelabs_api/types/monitoring_log_params.py
haizelabs_api/types/testing_create_evaluation_params.py
haizelabs_api/types/testing_create_evaluation_response.py
haizelabs_api/types/testing_start_params.py
haizelabs_api/types/testing_start_response.py
haizelabs_api/types/testing_update_evaluation_params.py
haizelabs_api/types/testing_update_params.py
haizelabs_api/types/testing_update_response.py
haizelabs_api/types/testing_write_score_params.py
haizelabs_api-0.1.0a16.dist-info/METADATA
haizelabs_api-0.1.0a16.dist-info/WHEEL
haizelabs_api-0.1.0a16.dist-info/licenses/LICENSE
haizelabs_api-0.1.0a16.dist-info/RECORD
