Metadata-Version: 2.4
Name: haizelabs_api
Version: 0.1.0a16
Summary: The official Python library for the Haize Labs API
Project-URL: Homepage, https://github.com/haizelabs/haizelabs-python
Project-URL: Repository, https://github.com/haizelabs/haizelabs-python
Author-email: Haize Labs <contact@haizelabs.com>
License-Expression: Apache-2.0
License-File: LICENSE
Classifier: Intended Audience :: Developers
Classifier: License :: OSI Approved :: Apache Software License
Classifier: Operating System :: MacOS
Classifier: Operating System :: Microsoft :: Windows
Classifier: Operating System :: OS Independent
Classifier: Operating System :: POSIX
Classifier: Operating System :: POSIX :: Linux
Classifier: Programming Language :: Python :: 3.8
Classifier: Programming Language :: Python :: 3.9
Classifier: Programming Language :: Python :: 3.10
Classifier: Programming Language :: Python :: 3.11
Classifier: Programming Language :: Python :: 3.12
Classifier: Topic :: Software Development :: Libraries :: Python Modules
Classifier: Typing :: Typed
Requires-Python: >=3.8
Requires-Dist: anyio<5,>=3.5.0
Requires-Dist: distro<2,>=1.7.0
Requires-Dist: httpx<1,>=0.23.0
Requires-Dist: pydantic<3,>=1.9.0
Requires-Dist: sniffio
Requires-Dist: typing-extensions<5,>=4.10
